meed-0.0.3.data/scripts/meed.py
meedlib/__init__.py
meedlib/base.py
meedlib/cli.py
meedlib/command.py
meedlib/config.py
meedlib/graph.py
meedlib/log.py
meedlib/stat.py
meedlib/terminal.py
meed-0.0.3.dist-info/METADATA
meed-0.0.3.dist-info/WHEEL
meed-0.0.3.dist-info/entry_points.txt
meed-0.0.3.dist-info/namespace_packages.txt
meed-0.0.3.dist-info/top_level.txt
meed-0.0.3.dist-info/zip-safe
meed-0.0.3.dist-info/RECORD
